django_unicorn_playground/__init__.py
django_unicorn_playground/cli.py
django_unicorn_playground/components.py
django_unicorn_playground/html/__init__.py
django_unicorn_playground/html/django.py
django_unicorn_playground/html/unicorn.py
django_unicorn_playground/main.py
django_unicorn_playground/settings.py
django_unicorn_playground/templates/base.html
django_unicorn_playground/urls.py
django_unicorn_playground/views.py
django_unicorn_playground-0.1.1.dist-info/LICENSE
django_unicorn_playground-0.1.1.dist-info/METADATA
django_unicorn_playground-0.1.1.dist-info/WHEEL
django_unicorn_playground-0.1.1.dist-info/entry_points.txt
django_unicorn_playground-0.1.1.dist-info/RECORD
