Metadata-Version: 2.1
Name: django-unicorn-playground
Version: 0.1.1
Summary: Prototype and debug `Unicorn` components without creating a complete Django application.
Home-page: https://github.com/adamghill/django-unicorn-playground/
License: MIT
Keywords: django,python,css,html
Author: adamghill
Author-email: adamghill@yahoo.com
Requires-Python: >=3.10,<4.0
Classifier: License :: OSI Approved :: MIT License
Classifier: Programming Language :: Python :: 3
Classifier: Programming Language :: Python :: 3.10
Classifier: Programming Language :: Python :: 3.11
Requires-Dist: click (>=8.1.7,<9.0.0)
Requires-Dist: django-unicorn (>=0.61.0)
Requires-Dist: rich-click (>=1.8,<2.0)
Requires-Dist: typeguard (>=4.3,<5.0)
Project-URL: Documentation, https://github.com/adamghill/django-unicorn-playground/
Project-URL: Funding, https://github.com/sponsors/adamghill
Project-URL: Repository, https://github.com/adamghill/django-unicorn-playground/
